{
  "id": "72d8904d-4c2b-420a-8bfb-fd4b10796765",
  "prevId": "00000000-0000-0000-0000-000000000000",
  "version": "7",
  "dialect": "postgresql",
  "tables": {
    "public.account": {
      "name": "account",
      "schema": "",
      "columns": {
        "id": {
          "name": "id",
          "type": "text",
          "primaryKey": true,
          "notNull": true
        },
        "account_id": {
          "name": "account_id",
          "type": "text",
          "primaryKey": false,
          "notNull": true
        },
        "provider_id": {
          "name": "provider_id",
          "type": "text",
          "primaryKey": false,
          "notNull": true
        },
        "user_id": {
          "name": "user_id",
          "type": "text",
          "primaryKey": false,
          "notNull": true
        },
        "access_token": {
          "name": "access_token",
          "type": "text",
          "primaryKey": false,
          "notNull": false
        },
        "refresh_token": {
          "name": "refresh_token",
          "type": "text",
          "primaryKey": false,
          "notNull": false
        },
        "id_token": {
          "name": "id_token",
          "type": "text",
          "primaryKey": false,
          "notNull": false
        },
        "access_token_expires_at": {
          "name": "access_token_expires_at",
          "type": "timestamp",
          "primaryKey": false,
          "notNull": false
        },
        "refresh_token_expires_at": {
          "name": "refresh_token_expires_at",
          "type": "timestamp",
          "primaryKey": false,
          "notNull": false
        },
        "scope": {
          "name": "scope",
          "type": "text",
          "primaryKey": false,
          "notNull": false
        },
        "password": {
          "name": "password",
          "type": "text",
          "primaryKey": false,
          "notNull": false
        },
        "created_at": {
          "name": "created_at",
          "type": "timestamp",
          "primaryKey": false,
          "notNull": true,
          "default": "now()"
        },
        "updated_at": {
          "name": "updated_at",
          "type": "timestamp",
          "primaryKey": false,
          "notNull": true
        }
      },
      "indexes": {
        "account_userId_idx": {
          "name": "account_userId_idx",
          "columns": [
            {
              "expression": "user_id",
              "isExpression": false,
              "asc": true,
              "nulls": "last"
            }
          ],
          "isUnique": false,
          "concurrently": false,
          "method": "btree",
          "with": {}
        }
      },
      "foreignKeys": {
        "account_user_id_user_id_fk": {
          "name": "account_user_id_user_id_fk",
          "tableFrom": "account",
          "tableTo": "user",
          "columnsFrom": [
            "user_id"
          ],
          "columnsTo": [
            "id"
          ],
          "onDelete": "cascade",
          "onUpdate": "no action"
        }
      },
      "compositePrimaryKeys": {},
      "uniqueConstraints": {},
      "policies": {},
      "checkConstraints": {},
      "isRLSEnabled": false
    },
    "public.asal_pembelian": {
      "name": "asal_pembelian",
      "schema": "",
      "columns": {
        "id": {
          "name": "id",
          "type": "integer",
          "primaryKey": true,
          "notNull": true,
          "identity": {
            "type": "always",
            "name": "asal_pembelian_id_seq",
            "schema": "public",
            "increment": "1",
            "startWith": "1",
            "minValue": "1",
            "maxValue": "2147483647",
            "cache": "1",
            "cycle": false
          }
        },
        "nama": {
          "name": "nama",
          "type": "text",
          "primaryKey": false,
          "notNull": true
        }
      },
      "indexes": {},
      "foreignKeys": {},
      "compositePrimaryKeys": {},
      "uniqueConstraints": {
        "asal_pembelian_nama_unique": {
          "name": "asal_pembelian_nama_unique",
          "nullsNotDistinct": false,
          "columns": [
            "nama"
          ]
        }
      },
      "policies": {},
      "checkConstraints": {},
      "isRLSEnabled": false
    },
    "public.barang": {
      "name": "barang",
      "schema": "",
      "columns": {
        "id": {
          "name": "id",
          "type": "integer",
          "primaryKey": true,
          "notNull": true,
          "identity": {
            "type": "always",
            "name": "barang_id_seq",
            "schema": "public",
            "increment": "1",
            "startWith": "1",
            "minValue": "1",
            "maxValue": "2147483647",
            "cache": "1",
            "cycle": false
          }
        },
        "nama": {
          "name": "nama",
          "type": "text",
          "primaryKey": false,
          "notNull": true
        },
        "kode_barang": {
          "name": "kode_barang",
          "type": "text",
          "primaryKey": false,
          "notNull": true
        },
        "stok": {
          "name": "stok",
          "type": "integer",
          "primaryKey": false,
          "notNull": true,
          "default": 0
        },
        "spesifikasi": {
          "name": "spesifikasi",
          "type": "text",
          "primaryKey": false,
          "notNull": false
        },
        "kategori_id": {
          "name": "kategori_id",
          "type": "integer",
          "primaryKey": false,
          "notNull": true
        },
        "satuan_id": {
          "name": "satuan_id",
          "type": "integer",
          "primaryKey": false,
          "notNull": true
        },
        "created_at": {
          "name": "created_at",
          "type": "timestamp",
          "primaryKey": false,
          "notNull": true,
          "default": "now()"
        },
        "updated_at": {
          "name": "updated_at",
          "type": "timestamp",
          "primaryKey": false,
          "notNull": true,
          "default": "now()"
        }
      },
      "indexes": {
        "barang_nama_idx": {
          "name": "barang_nama_idx",
          "columns": [
            {
              "expression": "nama",
              "isExpression": false,
              "asc": true,
              "nulls": "last"
            }
          ],
          "isUnique": false,
          "concurrently": false,
          "method": "btree",
          "with": {}
        }
      },
      "foreignKeys": {
        "barang_kategori_id_kategori_id_fk": {
          "name": "barang_kategori_id_kategori_id_fk",
          "tableFrom": "barang",
          "tableTo": "kategori",
          "columnsFrom": [
            "kategori_id"
          ],
          "columnsTo": [
            "id"
          ],
          "onDelete": "cascade",
          "onUpdate": "cascade"
        },
        "barang_satuan_id_satuan_id_fk": {
          "name": "barang_satuan_id_satuan_id_fk",
          "tableFrom": "barang",
          "tableTo": "satuan",
          "columnsFrom": [
            "satuan_id"
          ],
          "columnsTo": [
            "id"
          ],
          "onDelete": "cascade",
          "onUpdate": "cascade"
        }
      },
      "compositePrimaryKeys": {},
      "uniqueConstraints": {
        "barang_nama_unique": {
          "name": "barang_nama_unique",
          "nullsNotDistinct": false,
          "columns": [
            "nama"
          ]
        },
        "barang_kode_barang_unique": {
          "name": "barang_kode_barang_unique",
          "nullsNotDistinct": false,
          "columns": [
            "kode_barang"
          ]
        }
      },
      "policies": {},
      "checkConstraints": {},
      "isRLSEnabled": false
    },
    "public.bast_keluar": {
      "name": "bast_keluar",
      "schema": "",
      "columns": {
        "id": {
          "name": "id",
          "type": "integer",
          "primaryKey": true,
          "notNull": true,
          "identity": {
            "type": "always",
            "name": "bast_keluar_id_seq",
            "schema": "public",
            "increment": "1",
            "startWith": "1",
            "minValue": "1",
            "maxValue": "2147483647",
            "cache": "1",
            "cycle": false
          }
        },
        "sppb_id": {
          "name": "sppb_id",
          "type": "integer",
          "primaryKey": false,
          "notNull": true
        },
        "nomor_bast": {
          "name": "nomor_bast",
          "type": "text",
          "primaryKey": false,
          "notNull": true
        },
        "tanggal_bast": {
          "name": "tanggal_bast",
          "type": "date",
          "primaryKey": false,
          "notNull": true
        },
        "pihak_pertama_id": {
          "name": "pihak_pertama_id",
          "type": "integer",
          "primaryKey": false,
          "notNull": true
        },
        "pihak_kedua_id": {
          "name": "pihak_kedua_id",
          "type": "integer",
          "primaryKey": false,
          "notNull": true
        },
        "subtotal": {
          "name": "subtotal",
          "type": "numeric(18, 2)",
          "primaryKey": false,
          "notNull": true,
          "default": "'0'"
        },
        "total_ppn": {
          "name": "total_ppn",
          "type": "numeric(18, 2)",
          "primaryKey": false,
          "notNull": true,
          "default": "'0'"
        },
        "grand_total": {
          "name": "grand_total",
          "type": "numeric(18, 2)",
          "primaryKey": false,
          "notNull": true,
          "default": "'0'"
        },
        "is_printed": {
          "name": "is_printed",
          "type": "boolean",
          "primaryKey": false,
          "notNull": true,
          "default": false
        },
        "keterangan": {
          "name": "keterangan",
          "type": "text",
          "primaryKey": false,
          "notNull": false
        },
        "created_at": {
          "name": "created_at",
          "type": "timestamp",
          "primaryKey": false,
          "notNull": true,
          "default": "now()"
        },
        "updated_at": {
          "name": "updated_at",
          "type": "timestamp",
          "primaryKey": false,
          "notNull": false,
          "default": "now()"
        }
      },
      "indexes": {},
      "foreignKeys": {
        "bast_keluar_sppb_id_sppb_id_fk": {
          "name": "bast_keluar_sppb_id_sppb_id_fk",
          "tableFrom": "bast_keluar",
          "tableTo": "sppb",
          "columnsFrom": [
            "sppb_id"
          ],
          "columnsTo": [
            "id"
          ],
          "onDelete": "cascade",
          "onUpdate": "no action"
        },
        "bast_keluar_pihak_pertama_id_pegawai_id_fk": {
          "name": "bast_keluar_pihak_pertama_id_pegawai_id_fk",
          "tableFrom": "bast_keluar",
          "tableTo": "pegawai",
          "columnsFrom": [
            "pihak_pertama_id"
          ],
          "columnsTo": [
            "id"
          ],
          "onDelete": "no action",
          "onUpdate": "no action"
        },
        "bast_keluar_pihak_kedua_id_pegawai_id_fk": {
          "name": "bast_keluar_pihak_kedua_id_pegawai_id_fk",
          "tableFrom": "bast_keluar",
          "tableTo": "pegawai",
          "columnsFrom": [
            "pihak_kedua_id"
          ],
          "columnsTo": [
            "id"
          ],
          "onDelete": "no action",
          "onUpdate": "no action"
        }
      },
      "compositePrimaryKeys": {},
      "uniqueConstraints": {
        "bast_keluar_nomor_bast_unique": {
          "name": "bast_keluar_nomor_bast_unique",
          "nullsNotDistinct": false,
          "columns": [
            "nomor_bast"
          ]
        }
      },
      "policies": {},
      "checkConstraints": {},
      "isRLSEnabled": false
    },
    "public.bast_keluar_detail": {
      "name": "bast_keluar_detail",
      "schema": "",
      "columns": {
        "id": {
          "name": "id",
          "type": "integer",
          "primaryKey": true,
          "notNull": true,
          "identity": {
            "type": "always",
            "name": "bast_keluar_detail_id_seq",
            "schema": "public",
            "increment": "1",
            "startWith": "1",
            "minValue": "1",
            "maxValue": "2147483647",
            "cache": "1",
            "cycle": false
          }
        },
        "bast_keluar_id": {
          "name": "bast_keluar_id",
          "type": "integer",
          "primaryKey": false,
          "notNull": true
        },
        "barang_id": {
          "name": "barang_id",
          "type": "integer",
          "primaryKey": false,
          "notNull": true
        },
        "qty_serah_terima": {
          "name": "qty_serah_terima",
          "type": "integer",
          "primaryKey": false,
          "notNull": true
        },
        "harga_satuan": {
          "name": "harga_satuan",
          "type": "numeric(18, 2)",
          "primaryKey": false,
          "notNull": true,
          "default": "'0'"
        },
        "persentase_ppn": {
          "name": "persentase_ppn",
          "type": "integer",
          "primaryKey": false,
          "notNull": true,
          "default": 0
        },
        "nilai_ppn": {
          "name": "nilai_ppn",
          "type": "numeric(18, 2)",
          "primaryKey": false,
          "notNull": true,
          "default": "'0'"
        },
        "total_harga": {
          "name": "total_harga",
          "type": "numeric(18, 2)",
          "primaryKey": false,
          "notNull": true,
          "default": "'0'"
        },
        "keterangan": {
          "name": "keterangan",
          "type": "text",
          "primaryKey": false,
          "notNull": false
        }
      },
      "indexes": {},
      "foreignKeys": {
        "bast_keluar_detail_bast_keluar_id_bast_keluar_id_fk": {
          "name": "bast_keluar_detail_bast_keluar_id_bast_keluar_id_fk",
          "tableFrom": "bast_keluar_detail",
          "tableTo": "bast_keluar",
          "columnsFrom": [
            "bast_keluar_id"
          ],
          "columnsTo": [
            "id"
          ],
          "onDelete": "cascade",
          "onUpdate": "no action"
        },
        "bast_keluar_detail_barang_id_barang_id_fk": {
          "name": "bast_keluar_detail_barang_id_barang_id_fk",
          "tableFrom": "bast_keluar_detail",
          "tableTo": "barang",
          "columnsFrom": [
            "barang_id"
          ],
          "columnsTo": [
            "id"
          ],
          "onDelete": "no action",
          "onUpdate": "no action"
        }
      },
      "compositePrimaryKeys": {},
      "uniqueConstraints": {},
      "policies": {},
      "checkConstraints": {},
      "isRLSEnabled": false
    },
    "public.bast_masuk": {
      "name": "bast_masuk",
      "schema": "",
      "columns": {
        "id": {
          "name": "id",
          "type": "integer",
          "primaryKey": true,
          "notNull": true,
          "identity": {
            "type": "always",
            "name": "bast_masuk_id_seq",
            "schema": "public",
            "increment": "1",
            "startWith": "1",
            "minValue": "1",
            "maxValue": "2147483647",
            "cache": "1",
            "cycle": false
          }
        },
        "nomor_referensi": {
          "name": "nomor_referensi",
          "type": "text",
          "primaryKey": false,
          "notNull": true
        },
        "nomor_bast": {
          "name": "nomor_bast",
          "type": "text",
          "primaryKey": false,
          "notNull": true
        },
        "tanggal_bast": {
          "name": "tanggal_bast",
          "type": "date",
          "primaryKey": false,
          "notNull": true
        },
        "nomor_bapb": {
          "name": "nomor_bapb",
          "type": "text",
          "primaryKey": false,
          "notNull": true
        },
        "tanggal_bapb": {
          "name": "tanggal_bapb",
          "type": "date",
          "primaryKey": false,
          "notNull": true
        },
        "peruntukkan": {
          "name": "peruntukkan",
          "type": "text",
          "primaryKey": false,
          "notNull": false
        },
        "keterangan": {
          "name": "keterangan",
          "type": "text",
          "primaryKey": false,
          "notNull": false
        },
        "asal_pembelian_id": {
          "name": "asal_pembelian_id",
          "type": "integer",
          "primaryKey": false,
          "notNull": true
        },
        "rekening_id": {
          "name": "rekening_id",
          "type": "integer",
          "primaryKey": false,
          "notNull": true
        },
        "pihak_ketiga_id": {
          "name": "pihak_ketiga_id",
          "type": "integer",
          "primaryKey": false,
          "notNull": true
        },
        "pptk_ppk_id": {
          "name": "pptk_ppk_id",
          "type": "integer",
          "primaryKey": false,
          "notNull": true
        },
        "created_at": {
          "name": "created_at",
          "type": "timestamp",
          "primaryKey": false,
          "notNull": true,
          "default": "now()"
        },
        "updated_at": {
          "name": "updated_at",
          "type": "timestamp",
          "primaryKey": false,
          "notNull": true,
          "default": "now()"
        }
      },
      "indexes": {},
      "foreignKeys": {
        "bast_masuk_asal_pembelian_id_asal_pembelian_id_fk": {
          "name": "bast_masuk_asal_pembelian_id_asal_pembelian_id_fk",
          "tableFrom": "bast_masuk",
          "tableTo": "asal_pembelian",
          "columnsFrom": [
            "asal_pembelian_id"
          ],
          "columnsTo": [
            "id"
          ],
          "onDelete": "cascade",
          "onUpdate": "cascade"
        },
        "bast_masuk_rekening_id_rekening_id_fk": {
          "name": "bast_masuk_rekening_id_rekening_id_fk",
          "tableFrom": "bast_masuk",
          "tableTo": "rekening",
          "columnsFrom": [
            "rekening_id"
          ],
          "columnsTo": [
            "id"
          ],
          "onDelete": "cascade",
          "onUpdate": "cascade"
        },
        "bast_masuk_pihak_ketiga_id_pihak_ketiga_id_fk": {
          "name": "bast_masuk_pihak_ketiga_id_pihak_ketiga_id_fk",
          "tableFrom": "bast_masuk",
          "tableTo": "pihak_ketiga",
          "columnsFrom": [
            "pihak_ketiga_id"
          ],
          "columnsTo": [
            "id"
          ],
          "onDelete": "cascade",
          "onUpdate": "cascade"
        },
        "bast_masuk_pptk_ppk_id_pegawai_id_fk": {
          "name": "bast_masuk_pptk_ppk_id_pegawai_id_fk",
          "tableFrom": "bast_masuk",
          "tableTo": "pegawai",
          "columnsFrom": [
            "pptk_ppk_id"
          ],
          "columnsTo": [
            "id"
          ],
          "onDelete": "cascade",
          "onUpdate": "cascade"
        }
      },
      "compositePrimaryKeys": {},
      "uniqueConstraints": {
        "bast_masuk_nomor_referensi_unique": {
          "name": "bast_masuk_nomor_referensi_unique",
          "nullsNotDistinct": false,
          "columns": [
            "nomor_referensi"
          ]
        },
        "bast_masuk_nomor_bast_unique": {
          "name": "bast_masuk_nomor_bast_unique",
          "nullsNotDistinct": false,
          "columns": [
            "nomor_bast"
          ]
        },
        "bast_masuk_nomor_bapb_unique": {
          "name": "bast_masuk_nomor_bapb_unique",
          "nullsNotDistinct": false,
          "columns": [
            "nomor_bapb"
          ]
        }
      },
      "policies": {},
      "checkConstraints": {},
      "isRLSEnabled": false
    },
    "public.bast_masuk_detail": {
      "name": "bast_masuk_detail",
      "schema": "",
      "columns": {
        "id": {
          "name": "id",
          "type": "integer",
          "primaryKey": true,
          "notNull": true,
          "identity": {
            "type": "always",
            "name": "bast_masuk_detail_id_seq",
            "schema": "public",
            "increment": "1",
            "startWith": "1",
            "minValue": "1",
            "maxValue": "2147483647",
            "cache": "1",
            "cycle": false
          }
        },
        "bast_masuk_id": {
          "name": "bast_masuk_id",
          "type": "integer",
          "primaryKey": false,
          "notNull": true
        },
        "barang_id": {
          "name": "barang_id",
          "type": "integer",
          "primaryKey": false,
          "notNull": true
        },
        "qty": {
          "name": "qty",
          "type": "integer",
          "primaryKey": false,
          "notNull": true
        },
        "harga_satuan": {
          "name": "harga_satuan",
          "type": "numeric(18, 2)",
          "primaryKey": false,
          "notNull": true
        },
        "keterangan": {
          "name": "keterangan",
          "type": "text",
          "primaryKey": false,
          "notNull": false
        },
        "created_at": {
          "name": "created_at",
          "type": "timestamp",
          "primaryKey": false,
          "notNull": true,
          "default": "now()"
        },
        "updated_at": {
          "name": "updated_at",
          "type": "timestamp",
          "primaryKey": false,
          "notNull": true,
          "default": "now()"
        }
      },
      "indexes": {
        "bast_masuk_detail_bast_idx": {
          "name": "bast_masuk_detail_bast_idx",
          "columns": [
            {
              "expression": "bast_masuk_id",
              "isExpression": false,
              "asc": true,
              "nulls": "last"
            }
          ],
          "isUnique": false,
          "concurrently": false,
          "method": "btree",
          "with": {}
        },
        "bast_masuk_detail_barang_idx": {
          "name": "bast_masuk_detail_barang_idx",
          "columns": [
            {
              "expression": "barang_id",
              "isExpression": false,
              "asc": true,
              "nulls": "last"
            }
          ],
          "isUnique": false,
          "concurrently": false,
          "method": "btree",
          "with": {}
        },
        "bast_masuk_detail_bast_barang_ux": {
          "name": "bast_masuk_detail_bast_barang_ux",
          "columns": [
            {
              "expression": "bast_masuk_id",
              "isExpression": false,
              "asc": true,
              "nulls": "last"
            },
            {
              "expression": "barang_id",
              "isExpression": false,
              "asc": true,
              "nulls": "last"
            }
          ],
          "isUnique": true,
          "concurrently": false,
          "method": "btree",
          "with": {}
        }
      },
      "foreignKeys": {
        "bast_masuk_detail_bast_masuk_id_bast_masuk_id_fk": {
          "name": "bast_masuk_detail_bast_masuk_id_bast_masuk_id_fk",
          "tableFrom": "bast_masuk_detail",
          "tableTo": "bast_masuk",
          "columnsFrom": [
            "bast_masuk_id"
          ],
          "columnsTo": [
            "id"
          ],
          "onDelete": "cascade",
          "onUpdate": "cascade"
        },
        "bast_masuk_detail_barang_id_barang_id_fk": {
          "name": "bast_masuk_detail_barang_id_barang_id_fk",
          "tableFrom": "bast_masuk_detail",
          "tableTo": "barang",
          "columnsFrom": [
            "barang_id"
          ],
          "columnsTo": [
            "id"
          ],
          "onDelete": "cascade",
          "onUpdate": "cascade"
        }
      },
      "compositePrimaryKeys": {},
      "uniqueConstraints": {},
      "policies": {},
      "checkConstraints": {},
      "isRLSEnabled": false
    },
    "public.jabatan": {
      "name": "jabatan",
      "schema": "",
      "columns": {
        "id": {
          "name": "id",
          "type": "integer",
          "primaryKey": true,
          "notNull": true,
          "identity": {
            "type": "always",
            "name": "jabatan_id_seq",
            "schema": "public",
            "increment": "1",
            "startWith": "1",
            "minValue": "1",
            "maxValue": "2147483647",
            "cache": "1",
            "cycle": false
          }
        },
        "nama": {
          "name": "nama",
          "type": "text",
          "primaryKey": false,
          "notNull": true
        },
        "unit_kerja": {
          "name": "unit_kerja",
          "type": "text",
          "primaryKey": false,
          "notNull": false
        }
      },
      "indexes": {},
      "foreignKeys": {},
      "compositePrimaryKeys": {},
      "uniqueConstraints": {
        "jabatan_nama_unique": {
          "name": "jabatan_nama_unique",
          "nullsNotDistinct": false,
          "columns": [
            "nama"
          ]
        }
      },
      "policies": {},
      "checkConstraints": {},
      "isRLSEnabled": false
    },
    "public.kategori": {
      "name": "kategori",
      "schema": "",
      "columns": {
        "id": {
          "name": "id",
          "type": "integer",
          "primaryKey": true,
          "notNull": true,
          "identity": {
            "type": "always",
            "name": "kategori_id_seq",
            "schema": "public",
            "increment": "1",
            "startWith": "1",
            "minValue": "1",
            "maxValue": "2147483647",
            "cache": "1",
            "cycle": false
          }
        },
        "nama": {
          "name": "nama",
          "type": "text",
          "primaryKey": false,
          "notNull": true
        },
        "prefix": {
          "name": "prefix",
          "type": "text",
          "primaryKey": false,
          "notNull": true
        }
      },
      "indexes": {},
      "foreignKeys": {},
      "compositePrimaryKeys": {},
      "uniqueConstraints": {
        "kategori_nama_unique": {
          "name": "kategori_nama_unique",
          "nullsNotDistinct": false,
          "columns": [
            "nama"
          ]
        },
        "kategori_prefix_unique": {
          "name": "kategori_prefix_unique",
          "nullsNotDistinct": false,
          "columns": [
            "prefix"
          ]
        }
      },
      "policies": {},
      "checkConstraints": {},
      "isRLSEnabled": false
    },
    "public.mutasi_barang": {
      "name": "mutasi_barang",
      "schema": "",
      "columns": {
        "id": {
          "name": "id",
          "type": "integer",
          "primaryKey": true,
          "notNull": true,
          "identity": {
            "type": "always",
            "name": "mutasi_barang_id_seq",
            "schema": "public",
            "increment": "1",
            "startWith": "1",
            "minValue": "1",
            "maxValue": "2147483647",
            "cache": "1",
            "cycle": false
          }
        },
        "barang_id": {
          "name": "barang_id",
          "type": "integer",
          "primaryKey": false,
          "notNull": true
        },
        "tanggal": {
          "name": "tanggal",
          "type": "timestamp",
          "primaryKey": false,
          "notNull": true,
          "default": "now()"
        },
        "jenis_mutasi": {
          "name": "jenis_mutasi",
          "type": "jenis_mutasi",
          "typeSchema": "public",
          "primaryKey": false,
          "notNull": true
        },
        "qty_masuk": {
          "name": "qty_masuk",
          "type": "integer",
          "primaryKey": false,
          "notNull": true,
          "default": 0
        },
        "qty_keluar": {
          "name": "qty_keluar",
          "type": "integer",
          "primaryKey": false,
          "notNull": true,
          "default": 0
        },
        "stok_akhir": {
          "name": "stok_akhir",
          "type": "integer",
          "primaryKey": false,
          "notNull": true
        },
        "referensi_id": {
          "name": "referensi_id",
          "type": "text",
          "primaryKey": false,
          "notNull": false
        },
        "sumber_transaksi": {
          "name": "sumber_transaksi",
          "type": "text",
          "primaryKey": false,
          "notNull": false
        },
        "keterangan": {
          "name": "keterangan",
          "type": "text",
          "primaryKey": false,
          "notNull": false
        },
        "created_at": {
          "name": "created_at",
          "type": "timestamp",
          "primaryKey": false,
          "notNull": true,
          "default": "now()"
        }
      },
      "indexes": {
        "mutasi_history_idx": {
          "name": "mutasi_history_idx",
          "columns": [
            {
              "expression": "barang_id",
              "isExpression": false,
              "asc": true,
              "nulls": "last"
            },
            {
              "expression": "tanggal",
              "isExpression": false,
              "asc": true,
              "nulls": "last"
            }
          ],
          "isUnique": false,
          "concurrently": false,
          "method": "btree",
          "with": {}
        },
        "mutasi_barang_barang_idx": {
          "name": "mutasi_barang_barang_idx",
          "columns": [
            {
              "expression": "barang_id",
              "isExpression": false,
              "asc": true,
              "nulls": "last"
            }
          ],
          "isUnique": false,
          "concurrently": false,
          "method": "btree",
          "with": {}
        },
        "mutasi_barang_tanggal_idx": {
          "name": "mutasi_barang_tanggal_idx",
          "columns": [
            {
              "expression": "tanggal",
              "isExpression": false,
              "asc": true,
              "nulls": "last"
            }
          ],
          "isUnique": false,
          "concurrently": false,
          "method": "btree",
          "with": {}
        }
      },
      "foreignKeys": {
        "mutasi_barang_barang_id_barang_id_fk": {
          "name": "mutasi_barang_barang_id_barang_id_fk",
          "tableFrom": "mutasi_barang",
          "tableTo": "barang",
          "columnsFrom": [
            "barang_id"
          ],
          "columnsTo": [
            "id"
          ],
          "onDelete": "cascade",
          "onUpdate": "cascade"
        }
      },
      "compositePrimaryKeys": {},
      "uniqueConstraints": {},
      "policies": {},
      "checkConstraints": {},
      "isRLSEnabled": false
    },
    "public.pegawai": {
      "name": "pegawai",
      "schema": "",
      "columns": {
        "id": {
          "name": "id",
          "type": "integer",
          "primaryKey": true,
          "notNull": true,
          "identity": {
            "type": "always",
            "name": "pegawai_id_seq",
            "schema": "public",
            "increment": "1",
            "startWith": "1",
            "minValue": "1",
            "maxValue": "2147483647",
            "cache": "1",
            "cycle": false
          }
        },
        "nama": {
          "name": "nama",
          "type": "text",
          "primaryKey": false,
          "notNull": true
        },
        "nip": {
          "name": "nip",
          "type": "text",
          "primaryKey": false,
          "notNull": false
        },
        "user_id": {
          "name": "user_id",
          "type": "text",
          "primaryKey": false,
          "notNull": false
        },
        "created_at": {
          "name": "created_at",
          "type": "timestamp",
          "primaryKey": false,
          "notNull": true,
          "default": "now()"
        },
        "updated_at": {
          "name": "updated_at",
          "type": "timestamp",
          "primaryKey": false,
          "notNull": true,
          "default": "now()"
        }
      },
      "indexes": {},
      "foreignKeys": {
        "pegawai_user_id_user_id_fk": {
          "name": "pegawai_user_id_user_id_fk",
          "tableFrom": "pegawai",
          "tableTo": "user",
          "columnsFrom": [
            "user_id"
          ],
          "columnsTo": [
            "id"
          ],
          "onDelete": "set null",
          "onUpdate": "no action"
        }
      },
      "compositePrimaryKeys": {},
      "uniqueConstraints": {
        "pegawai_nip_unique": {
          "name": "pegawai_nip_unique",
          "nullsNotDistinct": false,
          "columns": [
            "nip"
          ]
        },
        "pegawai_user_id_unique": {
          "name": "pegawai_user_id_unique",
          "nullsNotDistinct": false,
          "columns": [
            "user_id"
          ]
        }
      },
      "policies": {},
      "checkConstraints": {},
      "isRLSEnabled": false
    },
    "public.pegawai_jabatan": {
      "name": "pegawai_jabatan",
      "schema": "",
      "columns": {
        "id": {
          "name": "id",
          "type": "integer",
          "primaryKey": true,
          "notNull": true,
          "identity": {
            "type": "always",
            "name": "pegawai_jabatan_id_seq",
            "schema": "public",
            "increment": "1",
            "startWith": "1",
            "minValue": "1",
            "maxValue": "2147483647",
            "cache": "1",
            "cycle": false
          }
        },
        "pegawai_id": {
          "name": "pegawai_id",
          "type": "integer",
          "primaryKey": false,
          "notNull": true
        },
        "jabatan_id": {
          "name": "jabatan_id",
          "type": "integer",
          "primaryKey": false,
          "notNull": true
        },
        "is_aktif": {
          "name": "is_aktif",
          "type": "boolean",
          "primaryKey": false,
          "notNull": true,
          "default": true
        },
        "created_at": {
          "name": "created_at",
          "type": "timestamp",
          "primaryKey": false,
          "notNull": true,
          "default": "now()"
        },
        "updated_at": {
          "name": "updated_at",
          "type": "timestamp",
          "primaryKey": false,
          "notNull": true,
          "default": "now()"
        }
      },
      "indexes": {},
      "foreignKeys": {
        "pegawai_jabatan_pegawai_id_pegawai_id_fk": {
          "name": "pegawai_jabatan_pegawai_id_pegawai_id_fk",
          "tableFrom": "pegawai_jabatan",
          "tableTo": "pegawai",
          "columnsFrom": [
            "pegawai_id"
          ],
          "columnsTo": [
            "id"
          ],
          "onDelete": "cascade",
          "onUpdate": "cascade"
        },
        "pegawai_jabatan_jabatan_id_jabatan_id_fk": {
          "name": "pegawai_jabatan_jabatan_id_jabatan_id_fk",
          "tableFrom": "pegawai_jabatan",
          "tableTo": "jabatan",
          "columnsFrom": [
            "jabatan_id"
          ],
          "columnsTo": [
            "id"
          ],
          "onDelete": "cascade",
          "onUpdate": "cascade"
        }
      },
      "compositePrimaryKeys": {},
      "uniqueConstraints": {},
      "policies": {},
      "checkConstraints": {},
      "isRLSEnabled": false
    },
    "public.pihak_ketiga": {
      "name": "pihak_ketiga",
      "schema": "",
      "columns": {
        "id": {
          "name": "id",
          "type": "integer",
          "primaryKey": true,
          "notNull": true,
          "identity": {
            "type": "always",
            "name": "pihak_ketiga_id_seq",
            "schema": "public",
            "increment": "1",
            "startWith": "1",
            "minValue": "1",
            "maxValue": "2147483647",
            "cache": "1",
            "cycle": false
          }
        },
        "nama": {
          "name": "nama",
          "type": "text",
          "primaryKey": false,
          "notNull": true
        }
      },
      "indexes": {},
      "foreignKeys": {},
      "compositePrimaryKeys": {},
      "uniqueConstraints": {
        "pihak_ketiga_nama_unique": {
          "name": "pihak_ketiga_nama_unique",
          "nullsNotDistinct": false,
          "columns": [
            "nama"
          ]
        }
      },
      "policies": {},
      "checkConstraints": {},
      "isRLSEnabled": false
    },
    "public.rekening": {
      "name": "rekening",
      "schema": "",
      "columns": {
        "id": {
          "name": "id",
          "type": "integer",
          "primaryKey": true,
          "notNull": true,
          "identity": {
            "type": "always",
            "name": "rekening_id_seq",
            "schema": "public",
            "increment": "1",
            "startWith": "1",
            "minValue": "1",
            "maxValue": "2147483647",
            "cache": "1",
            "cycle": false
          }
        },
        "nama_bank": {
          "name": "nama_bank",
          "type": "text",
          "primaryKey": false,
          "notNull": true
        },
        "nomor_rekening": {
          "name": "nomor_rekening",
          "type": "text",
          "primaryKey": false,
          "notNull": true
        },
        "nama_pemilik": {
          "name": "nama_pemilik",
          "type": "text",
          "primaryKey": false,
          "notNull": true
        },
        "keterangan": {
          "name": "keterangan",
          "type": "text",
          "primaryKey": false,
          "notNull": false
        }
      },
      "indexes": {},
      "foreignKeys": {},
      "compositePrimaryKeys": {},
      "uniqueConstraints": {
        "rekening_nomor_rekening_unique": {
          "name": "rekening_nomor_rekening_unique",
          "nullsNotDistinct": false,
          "columns": [
            "nomor_rekening"
          ]
        }
      },
      "policies": {},
      "checkConstraints": {},
      "isRLSEnabled": false
    },
    "public.satuan": {
      "name": "satuan",
      "schema": "",
      "columns": {
        "id": {
          "name": "id",
          "type": "integer",
          "primaryKey": true,
          "notNull": true,
          "identity": {
            "type": "always",
            "name": "satuan_id_seq",
            "schema": "public",
            "increment": "1",
            "startWith": "1",
            "minValue": "1",
            "maxValue": "2147483647",
            "cache": "1",
            "cycle": false
          }
        },
        "nama": {
          "name": "nama",
          "type": "text",
          "primaryKey": false,
          "notNull": true
        }
      },
      "indexes": {},
      "foreignKeys": {},
      "compositePrimaryKeys": {},
      "uniqueConstraints": {
        "satuan_nama_unique": {
          "name": "satuan_nama_unique",
          "nullsNotDistinct": false,
          "columns": [
            "nama"
          ]
        }
      },
      "policies": {},
      "checkConstraints": {},
      "isRLSEnabled": false
    },
    "public.session": {
      "name": "session",
      "schema": "",
      "columns": {
        "id": {
          "name": "id",
          "type": "text",
          "primaryKey": true,
          "notNull": true
        },
        "expires_at": {
          "name": "expires_at",
          "type": "timestamp",
          "primaryKey": false,
          "notNull": true
        },
        "token": {
          "name": "token",
          "type": "text",
          "primaryKey": false,
          "notNull": true
        },
        "created_at": {
          "name": "created_at",
          "type": "timestamp",
          "primaryKey": false,
          "notNull": true,
          "default": "now()"
        },
        "updated_at": {
          "name": "updated_at",
          "type": "timestamp",
          "primaryKey": false,
          "notNull": true
        },
        "ip_address": {
          "name": "ip_address",
          "type": "text",
          "primaryKey": false,
          "notNull": false
        },
        "user_agent": {
          "name": "user_agent",
          "type": "text",
          "primaryKey": false,
          "notNull": false
        },
        "user_id": {
          "name": "user_id",
          "type": "text",
          "primaryKey": false,
          "notNull": true
        },
        "impersonated_by": {
          "name": "impersonated_by",
          "type": "text",
          "primaryKey": false,
          "notNull": false
        }
      },
      "indexes": {
        "session_userId_idx": {
          "name": "session_userId_idx",
          "columns": [
            {
              "expression": "user_id",
              "isExpression": false,
              "asc": true,
              "nulls": "last"
            }
          ],
          "isUnique": false,
          "concurrently": false,
          "method": "btree",
          "with": {}
        }
      },
      "foreignKeys": {
        "session_user_id_user_id_fk": {
          "name": "session_user_id_user_id_fk",
          "tableFrom": "session",
          "tableTo": "user",
          "columnsFrom": [
            "user_id"
          ],
          "columnsTo": [
            "id"
          ],
          "onDelete": "cascade",
          "onUpdate": "no action"
        }
      },
      "compositePrimaryKeys": {},
      "uniqueConstraints": {
        "session_token_unique": {
          "name": "session_token_unique",
          "nullsNotDistinct": false,
          "columns": [
            "token"
          ]
        }
      },
      "policies": {},
      "checkConstraints": {},
      "isRLSEnabled": false
    },
    "public.spb": {
      "name": "spb",
      "schema": "",
      "columns": {
        "id": {
          "name": "id",
          "type": "integer",
          "primaryKey": true,
          "notNull": true,
          "identity": {
            "type": "always",
            "name": "spb_id_seq",
            "schema": "public",
            "increment": "1",
            "startWith": "1",
            "minValue": "1",
            "maxValue": "2147483647",
            "cache": "1",
            "cycle": false
          }
        },
        "nomor_spb": {
          "name": "nomor_spb",
          "type": "text",
          "primaryKey": false,
          "notNull": true
        },
        "tanggal_spb": {
          "name": "tanggal_spb",
          "type": "date",
          "primaryKey": false,
          "notNull": true
        },
        "pemohon_id": {
          "name": "pemohon_id",
          "type": "integer",
          "primaryKey": false,
          "notNull": true
        },
        "status": {
          "name": "status",
          "type": "status_spb",
          "typeSchema": "public",
          "primaryKey": false,
          "notNull": true,
          "default": "'MENUNGGU_SPPB'"
        },
        "is_printed": {
          "name": "is_printed",
          "type": "boolean",
          "primaryKey": false,
          "notNull": true,
          "default": false
        },
        "keterangan": {
          "name": "keterangan",
          "type": "text",
          "primaryKey": false,
          "notNull": false
        },
        "created_at": {
          "name": "created_at",
          "type": "timestamp",
          "primaryKey": false,
          "notNull": true,
          "default": "now()"
        },
        "updated_at": {
          "name": "updated_at",
          "type": "timestamp",
          "primaryKey": false,
          "notNull": true,
          "default": "now()"
        }
      },
      "indexes": {},
      "foreignKeys": {
        "spb_pemohon_id_pegawai_id_fk": {
          "name": "spb_pemohon_id_pegawai_id_fk",
          "tableFrom": "spb",
          "tableTo": "pegawai",
          "columnsFrom": [
            "pemohon_id"
          ],
          "columnsTo": [
            "id"
          ],
          "onDelete": "cascade",
          "onUpdate": "cascade"
        }
      },
      "compositePrimaryKeys": {},
      "uniqueConstraints": {
        "spb_nomor_spb_unique": {
          "name": "spb_nomor_spb_unique",
          "nullsNotDistinct": false,
          "columns": [
            "nomor_spb"
          ]
        }
      },
      "policies": {},
      "checkConstraints": {},
      "isRLSEnabled": false
    },
    "public.spb_detail": {
      "name": "spb_detail",
      "schema": "",
      "columns": {
        "id": {
          "name": "id",
          "type": "integer",
          "primaryKey": true,
          "notNull": true,
          "identity": {
            "type": "always",
            "name": "spb_detail_id_seq",
            "schema": "public",
            "increment": "1",
            "startWith": "1",
            "minValue": "1",
            "maxValue": "2147483647",
            "cache": "1",
            "cycle": false
          }
        },
        "spb_id": {
          "name": "spb_id",
          "type": "integer",
          "primaryKey": false,
          "notNull": true
        },
        "barang_id": {
          "name": "barang_id",
          "type": "integer",
          "primaryKey": false,
          "notNull": true
        },
        "qty_permintaan": {
          "name": "qty_permintaan",
          "type": "integer",
          "primaryKey": false,
          "notNull": true
        },
        "keterangan": {
          "name": "keterangan",
          "type": "text",
          "primaryKey": false,
          "notNull": false
        }
      },
      "indexes": {},
      "foreignKeys": {
        "spb_detail_spb_id_spb_id_fk": {
          "name": "spb_detail_spb_id_spb_id_fk",
          "tableFrom": "spb_detail",
          "tableTo": "spb",
          "columnsFrom": [
            "spb_id"
          ],
          "columnsTo": [
            "id"
          ],
          "onDelete": "cascade",
          "onUpdate": "cascade"
        },
        "spb_detail_barang_id_barang_id_fk": {
          "name": "spb_detail_barang_id_barang_id_fk",
          "tableFrom": "spb_detail",
          "tableTo": "barang",
          "columnsFrom": [
            "barang_id"
          ],
          "columnsTo": [
            "id"
          ],
          "onDelete": "no action",
          "onUpdate": "no action"
        }
      },
      "compositePrimaryKeys": {},
      "uniqueConstraints": {},
      "policies": {},
      "checkConstraints": {},
      "isRLSEnabled": false
    },
    "public.sppb": {
      "name": "sppb",
      "schema": "",
      "columns": {
        "id": {
          "name": "id",
          "type": "integer",
          "primaryKey": true,
          "notNull": true,
          "identity": {
            "type": "always",
            "name": "sppb_id_seq",
            "schema": "public",
            "increment": "1",
            "startWith": "1",
            "minValue": "1",
            "maxValue": "2147483647",
            "cache": "1",
            "cycle": false
          }
        },
        "nomor_sppb": {
          "name": "nomor_sppb",
          "type": "text",
          "primaryKey": false,
          "notNull": true
        },
        "tanggal_sppb": {
          "name": "tanggal_sppb",
          "type": "date",
          "primaryKey": false,
          "notNull": true
        },
        "spb_id": {
          "name": "spb_id",
          "type": "integer",
          "primaryKey": false,
          "notNull": true
        },
        "pembuat_id": {
          "name": "pembuat_id",
          "type": "integer",
          "primaryKey": false,
          "notNull": false
        },
        "pejabat_penyetuju_id": {
          "name": "pejabat_penyetuju_id",
          "type": "integer",
          "primaryKey": false,
          "notNull": true
        },
        "serah_terima_oleh_id": {
          "name": "serah_terima_oleh_id",
          "type": "integer",
          "primaryKey": false,
          "notNull": false
        },
        "diterima_oleh_id": {
          "name": "diterima_oleh_id",
          "type": "integer",
          "primaryKey": false,
          "notNull": true
        },
        "keterangan": {
          "name": "keterangan",
          "type": "text",
          "primaryKey": false,
          "notNull": false
        },
        "status": {
          "name": "status",
          "type": "status_sppb",
          "typeSchema": "public",
          "primaryKey": false,
          "notNull": true,
          "default": "'MENUNGGU_BAST'"
        },
        "is_printed": {
          "name": "is_printed",
          "type": "boolean",
          "primaryKey": false,
          "notNull": true,
          "default": false
        },
        "created_at": {
          "name": "created_at",
          "type": "timestamp",
          "primaryKey": false,
          "notNull": true,
          "default": "now()"
        },
        "updated_at": {
          "name": "updated_at",
          "type": "timestamp",
          "primaryKey": false,
          "notNull": false,
          "default": "now()"
        }
      },
      "indexes": {},
      "foreignKeys": {
        "sppb_spb_id_spb_id_fk": {
          "name": "sppb_spb_id_spb_id_fk",
          "tableFrom": "sppb",
          "tableTo": "spb",
          "columnsFrom": [
            "spb_id"
          ],
          "columnsTo": [
            "id"
          ],
          "onDelete": "cascade",
          "onUpdate": "no action"
        },
        "sppb_pembuat_id_pegawai_id_fk": {
          "name": "sppb_pembuat_id_pegawai_id_fk",
          "tableFrom": "sppb",
          "tableTo": "pegawai",
          "columnsFrom": [
            "pembuat_id"
          ],
          "columnsTo": [
            "id"
          ],
          "onDelete": "no action",
          "onUpdate": "no action"
        },
        "sppb_pejabat_penyetuju_id_pegawai_id_fk": {
          "name": "sppb_pejabat_penyetuju_id_pegawai_id_fk",
          "tableFrom": "sppb",
          "tableTo": "pegawai",
          "columnsFrom": [
            "pejabat_penyetuju_id"
          ],
          "columnsTo": [
            "id"
          ],
          "onDelete": "no action",
          "onUpdate": "no action"
        },
        "sppb_serah_terima_oleh_id_pegawai_id_fk": {
          "name": "sppb_serah_terima_oleh_id_pegawai_id_fk",
          "tableFrom": "sppb",
          "tableTo": "pegawai",
          "columnsFrom": [
            "serah_terima_oleh_id"
          ],
          "columnsTo": [
            "id"
          ],
          "onDelete": "no action",
          "onUpdate": "no action"
        },
        "sppb_diterima_oleh_id_pegawai_id_fk": {
          "name": "sppb_diterima_oleh_id_pegawai_id_fk",
          "tableFrom": "sppb",
          "tableTo": "pegawai",
          "columnsFrom": [
            "diterima_oleh_id"
          ],
          "columnsTo": [
            "id"
          ],
          "onDelete": "no action",
          "onUpdate": "no action"
        }
      },
      "compositePrimaryKeys": {},
      "uniqueConstraints": {
        "sppb_nomor_sppb_unique": {
          "name": "sppb_nomor_sppb_unique",
          "nullsNotDistinct": false,
          "columns": [
            "nomor_sppb"
          ]
        }
      },
      "policies": {},
      "checkConstraints": {},
      "isRLSEnabled": false
    },
    "public.sppb_detail": {
      "name": "sppb_detail",
      "schema": "",
      "columns": {
        "id": {
          "name": "id",
          "type": "integer",
          "primaryKey": true,
          "notNull": true,
          "identity": {
            "type": "always",
            "name": "sppb_detail_id_seq",
            "schema": "public",
            "increment": "1",
            "startWith": "1",
            "minValue": "1",
            "maxValue": "2147483647",
            "cache": "1",
            "cycle": false
          }
        },
        "sppb_id": {
          "name": "sppb_id",
          "type": "integer",
          "primaryKey": false,
          "notNull": true
        },
        "barang_id": {
          "name": "barang_id",
          "type": "integer",
          "primaryKey": false,
          "notNull": true
        },
        "qty_disetujui": {
          "name": "qty_disetujui",
          "type": "integer",
          "primaryKey": false,
          "notNull": true
        },
        "keterangan": {
          "name": "keterangan",
          "type": "text",
          "primaryKey": false,
          "notNull": false
        }
      },
      "indexes": {},
      "foreignKeys": {
        "sppb_detail_sppb_id_sppb_id_fk": {
          "name": "sppb_detail_sppb_id_sppb_id_fk",
          "tableFrom": "sppb_detail",
          "tableTo": "sppb",
          "columnsFrom": [
            "sppb_id"
          ],
          "columnsTo": [
            "id"
          ],
          "onDelete": "cascade",
          "onUpdate": "no action"
        },
        "sppb_detail_barang_id_barang_id_fk": {
          "name": "sppb_detail_barang_id_barang_id_fk",
          "tableFrom": "sppb_detail",
          "tableTo": "barang",
          "columnsFrom": [
            "barang_id"
          ],
          "columnsTo": [
            "id"
          ],
          "onDelete": "no action",
          "onUpdate": "no action"
        }
      },
      "compositePrimaryKeys": {},
      "uniqueConstraints": {},
      "policies": {},
      "checkConstraints": {},
      "isRLSEnabled": false
    },
    "public.stock_opname": {
      "name": "stock_opname",
      "schema": "",
      "columns": {
        "id": {
          "name": "id",
          "type": "integer",
          "primaryKey": true,
          "notNull": true,
          "identity": {
            "type": "always",
            "name": "stock_opname_id_seq",
            "schema": "public",
            "increment": "1",
            "startWith": "1",
            "minValue": "1",
            "maxValue": "2147483647",
            "cache": "1",
            "cycle": false
          }
        },
        "nomor": {
          "name": "nomor",
          "type": "text",
          "primaryKey": false,
          "notNull": true
        },
        "tanggal": {
          "name": "tanggal",
          "type": "date",
          "primaryKey": false,
          "notNull": true
        },
        "keterangan": {
          "name": "keterangan",
          "type": "text",
          "primaryKey": false,
          "notNull": false
        },
        "status": {
          "name": "status",
          "type": "stock_opname_status",
          "typeSchema": "public",
          "primaryKey": false,
          "notNull": true,
          "default": "'DRAFT'"
        },
        "petugas_id": {
          "name": "petugas_id",
          "type": "integer",
          "primaryKey": false,
          "notNull": false
        },
        "created_at": {
          "name": "created_at",
          "type": "timestamp",
          "primaryKey": false,
          "notNull": true,
          "default": "now()"
        },
        "updated_at": {
          "name": "updated_at",
          "type": "timestamp",
          "primaryKey": false,
          "notNull": true,
          "default": "now()"
        }
      },
      "indexes": {},
      "foreignKeys": {
        "stock_opname_petugas_id_pegawai_id_fk": {
          "name": "stock_opname_petugas_id_pegawai_id_fk",
          "tableFrom": "stock_opname",
          "tableTo": "pegawai",
          "columnsFrom": [
            "petugas_id"
          ],
          "columnsTo": [
            "id"
          ],
          "onDelete": "no action",
          "onUpdate": "no action"
        }
      },
      "compositePrimaryKeys": {},
      "uniqueConstraints": {
        "stock_opname_nomor_unique": {
          "name": "stock_opname_nomor_unique",
          "nullsNotDistinct": false,
          "columns": [
            "nomor"
          ]
        }
      },
      "policies": {},
      "checkConstraints": {},
      "isRLSEnabled": false
    },
    "public.stock_opname_detail": {
      "name": "stock_opname_detail",
      "schema": "",
      "columns": {
        "id": {
          "name": "id",
          "type": "integer",
          "primaryKey": true,
          "notNull": true,
          "identity": {
            "type": "always",
            "name": "stock_opname_detail_id_seq",
            "schema": "public",
            "increment": "1",
            "startWith": "1",
            "minValue": "1",
            "maxValue": "2147483647",
            "cache": "1",
            "cycle": false
          }
        },
        "stock_opname_id": {
          "name": "stock_opname_id",
          "type": "integer",
          "primaryKey": false,
          "notNull": true
        },
        "barang_id": {
          "name": "barang_id",
          "type": "integer",
          "primaryKey": false,
          "notNull": true
        },
        "stok_sistem": {
          "name": "stok_sistem",
          "type": "integer",
          "primaryKey": false,
          "notNull": true
        },
        "stok_fisik": {
          "name": "stok_fisik",
          "type": "integer",
          "primaryKey": false,
          "notNull": true
        },
        "selisih": {
          "name": "selisih",
          "type": "integer",
          "primaryKey": false,
          "notNull": true
        },
        "keterangan": {
          "name": "keterangan",
          "type": "text",
          "primaryKey": false,
          "notNull": false
        }
      },
      "indexes": {},
      "foreignKeys": {
        "stock_opname_detail_stock_opname_id_stock_opname_id_fk": {
          "name": "stock_opname_detail_stock_opname_id_stock_opname_id_fk",
          "tableFrom": "stock_opname_detail",
          "tableTo": "stock_opname",
          "columnsFrom": [
            "stock_opname_id"
          ],
          "columnsTo": [
            "id"
          ],
          "onDelete": "cascade",
          "onUpdate": "no action"
        },
        "stock_opname_detail_barang_id_barang_id_fk": {
          "name": "stock_opname_detail_barang_id_barang_id_fk",
          "tableFrom": "stock_opname_detail",
          "tableTo": "barang",
          "columnsFrom": [
            "barang_id"
          ],
          "columnsTo": [
            "id"
          ],
          "onDelete": "no action",
          "onUpdate": "no action"
        }
      },
      "compositePrimaryKeys": {},
      "uniqueConstraints": {},
      "policies": {},
      "checkConstraints": {},
      "isRLSEnabled": false
    },
    "public.user": {
      "name": "user",
      "schema": "",
      "columns": {
        "id": {
          "name": "id",
          "type": "text",
          "primaryKey": true,
          "notNull": true
        },
        "name": {
          "name": "name",
          "type": "text",
          "primaryKey": false,
          "notNull": true
        },
        "email": {
          "name": "email",
          "type": "text",
          "primaryKey": false,
          "notNull": true
        },
        "email_verified": {
          "name": "email_verified",
          "type": "boolean",
          "primaryKey": false,
          "notNull": true,
          "default": false
        },
        "image": {
          "name": "image",
          "type": "text",
          "primaryKey": false,
          "notNull": false
        },
        "created_at": {
          "name": "created_at",
          "type": "timestamp",
          "primaryKey": false,
          "notNull": true,
          "default": "now()"
        },
        "updated_at": {
          "name": "updated_at",
          "type": "timestamp",
          "primaryKey": false,
          "notNull": true,
          "default": "now()"
        },
        "role": {
          "name": "role",
          "type": "text",
          "primaryKey": false,
          "notNull": false
        },
        "banned": {
          "name": "banned",
          "type": "boolean",
          "primaryKey": false,
          "notNull": false,
          "default": false
        },
        "ban_reason": {
          "name": "ban_reason",
          "type": "text",
          "primaryKey": false,
          "notNull": false
        },
        "ban_expires": {
          "name": "ban_expires",
          "type": "timestamp",
          "primaryKey": false,
          "notNull": false
        }
      },
      "indexes": {},
      "foreignKeys": {},
      "compositePrimaryKeys": {},
      "uniqueConstraints": {
        "user_email_unique": {
          "name": "user_email_unique",
          "nullsNotDistinct": false,
          "columns": [
            "email"
          ]
        }
      },
      "policies": {},
      "checkConstraints": {},
      "isRLSEnabled": false
    },
    "public.verification": {
      "name": "verification",
      "schema": "",
      "columns": {
        "id": {
          "name": "id",
          "type": "text",
          "primaryKey": true,
          "notNull": true
        },
        "identifier": {
          "name": "identifier",
          "type": "text",
          "primaryKey": false,
          "notNull": true
        },
        "value": {
          "name": "value",
          "type": "text",
          "primaryKey": false,
          "notNull": true
        },
        "expires_at": {
          "name": "expires_at",
          "type": "timestamp",
          "primaryKey": false,
          "notNull": true
        },
        "created_at": {
          "name": "created_at",
          "type": "timestamp",
          "primaryKey": false,
          "notNull": true,
          "default": "now()"
        },
        "updated_at": {
          "name": "updated_at",
          "type": "timestamp",
          "primaryKey": false,
          "notNull": true,
          "default": "now()"
        }
      },
      "indexes": {
        "verification_identifier_idx": {
          "name": "verification_identifier_idx",
          "columns": [
            {
              "expression": "identifier",
              "isExpression": false,
              "asc": true,
              "nulls": "last"
            }
          ],
          "isUnique": false,
          "concurrently": false,
          "method": "btree",
          "with": {}
        }
      },
      "foreignKeys": {},
      "compositePrimaryKeys": {},
      "uniqueConstraints": {},
      "policies": {},
      "checkConstraints": {},
      "isRLSEnabled": false
    }
  },
  "enums": {
    "public.jenis_mutasi": {
      "name": "jenis_mutasi",
      "schema": "public",
      "values": [
        "MASUK",
        "KELUAR",
        "PENYESUAIAN"
      ]
    },
    "public.status_spb": {
      "name": "status_spb",
      "schema": "public",
      "values": [
        "MENUNGGU_SPPB",
        "SELESAI",
        "BATAL"
      ]
    },
    "public.status_sppb": {
      "name": "status_sppb",
      "schema": "public",
      "values": [
        "MENUNGGU_BAST",
        "SELESAI",
        "BATAL"
      ]
    },
    "public.stock_opname_status": {
      "name": "stock_opname_status",
      "schema": "public",
      "values": [
        "DRAFT",
        "COMPLETED",
        "CANCELLED"
      ]
    }
  },
  "schemas": {},
  "sequences": {},
  "roles": {},
  "policies": {},
  "views": {},
  "_meta": {
    "columns": {},
    "schemas": {},
    "tables": {}
  }
}